__init__.py
gdb_value_to_json.py
gdb2json-3.0.0.dist-info/LICENSE.txt
gdb2json-3.0.0.dist-info/METADATA
gdb2json-3.0.0.dist-info/WHEEL
gdb2json-3.0.0.dist-info/entry_points.txt
gdb2json-3.0.0.dist-info/top_level.txt
gdb2json-3.0.0.dist-info/RECORD
